descriptools/__init__.py
descriptools/downslope.py
descriptools/evaluation.py
descriptools/flowhand.py
descriptools/gfi.py
descriptools/helpers.py
descriptools/slope.py
descriptools/topoindexes.py
descriptools-1.0.3.dist-info/LICENSE.txt
descriptools-1.0.3.dist-info/METADATA
descriptools-1.0.3.dist-info/WHEEL
descriptools-1.0.3.dist-info/top_level.txt
descriptools-1.0.3.dist-info/RECORD
