Metadata-Version: 2.1
Name: descriptools
Version: 1.0.3
Summary: A gpu-based toolbox for terrain descriptor calculation/delineation
Home-page: https://github.com/JVBSouza/descriptools
License: MIT
Download-URL: https://github.com/JVBSouza/descriptools/archive/master.zip
Keywords: hidrology,gis,flood
Platform: UNKNOWN
Classifier: Programming Language :: Python :: 3
Classifier: License :: OSI Approved :: MIT License
Classifier: Operating System :: OS Independent
Classifier: Environment :: GPU :: NVIDIA CUDA
License-File: LICENSE.txt
Requires-Dist: numpy
Requires-Dist: numba
